{
    "market_type": "futures",
    "user": "bybit_readonly",
    "symbols": [
        "HBARUSDT"
    ],
    "latency_simulation_ms": 1000,
    "starting_balance": 1000.0,
    "start_date": "2020-06-14",
    "end_date": "2024-06-13",
    "slim_analysis": true,
    "base_dir": "/home/user/passivbot/backtests/pbgui",
    "ohlcv": true,
    "adg_n_subdivisions": 10,
    "enable_interactive_plot": false,
    "plot_theme": "light",
    "plot_candles_interval": "1m",
    "spot": false,
    "exchange": "bybit",
    "session_name": "2020-06-14_2024-06-13",
    "symbol": "HBARUSDT",
    "caches_dirpath": "/home/user/passivbot/backtests/pbgui/bybit/HBARUSDT/caches/",
    "plots_dirpath": "/home/user/passivbot/backtests/pbgui/bybit/HBARUSDT/plots/2024-06-24T120625/",
    "c_mult": 1.0,
    "hedge_mode": true,
    "inverse": false,
    "maker_fee": 0.0002,
    "min_cost": 0.0,
    "min_qty": 1.0,
    "price_step": 1e-05,
    "qty_step": 1.0,
    "taker_fee": 0.00055,
    "n_parts": null,
    "config_name": "recursive_grid_1_symbols_1460days",
    "logging_level": 0,
    "long": {
        "auto_unstuck_delay_minutes": 0,
        "auto_unstuck_ema_dist": 0,
        "auto_unstuck_qty_pct": 0.0,
        "auto_unstuck_wallet_exposure_threshold": 0.0,
        "backwards_tp": false,
        "ddown_factor": 0.47798114261688246,
        "ema_span_0": 1308.870912185589,
        "ema_span_1": 1242.1415755742887,
        "enabled": true,
        "initial_eprice_ema_dist": 0.026509414789983532,
        "initial_qty_pct": 0.04,
        "markup_range": 0.03785954000216831,
        "min_markup": 0.010433475221825604,
        "n_close_orders": 2,
        "rentry_pprice_dist": 0.01883905672205768,
        "rentry_pprice_dist_wallet_exposure_weighting": 9.278009887588777,
        "wallet_exposure_limit": 1
    },
    "short": {
        "auto_unstuck_delay_minutes": 791.1946648788355,
        "auto_unstuck_ema_dist": -0.03558589047830871,
        "auto_unstuck_qty_pct": 0.07511623926583437,
        "auto_unstuck_wallet_exposure_threshold": 0.19773181527718178,
        "backwards_tp": false,
        "ddown_factor": 0.686844573104043,
        "ema_span_0": 840.298831307171,
        "ema_span_1": 476.55895107918866,
        "enabled": false,
        "initial_eprice_ema_dist": -0.04345217922940716,
        "initial_qty_pct": 0.026472962782734935,
        "markup_range": 0.05768530352037857,
        "min_markup": 0.006692739697799839,
        "n_close_orders": 3,
        "rentry_pprice_dist": 0.032908434661060644,
        "rentry_pprice_dist_wallet_exposure_weighting": 14.885344973518905,
        "wallet_exposure_limit": 1.0
    },
    "disable_plotting": true,
    "passivbot_mode": "recursive_grid",
    "n_days": 961.7,
    "result": {
        "adg_long": 0.0008549849120029762,
        "adg_per_exposure_long": 0.0008549849120029762,
        "adg_per_exposure_short": 0.0,
        "adg_short": 0.0,
        "adg_weighted_long": 0.0012224005856623422,
        "adg_weighted_per_exposure_long": 0.0012224005856623422,
        "adg_weighted_per_exposure_short": 0.0,
        "adg_weighted_short": 0.0,
        "avg_fills_per_day_long": 7.104332755632583,
        "avg_fills_per_day_short": 0.0,
        "closest_bkr_long": 0.9998758445610645,
        "closest_bkr_short": 1.0,
        "drawdown_1pct_worst_mean_long": 0.1353043052321256,
        "drawdown_1pct_worst_mean_short": -0.0,
        "drawdown_max_long": 0.1916945076542913,
        "drawdown_max_short": -0.0,
        "eqbal_ratio_mean_long": 0.9966271254819918,
        "eqbal_ratio_mean_of_10_worst_long": 0.8188189445102771,
        "eqbal_ratio_mean_of_10_worst_short": 1.0,
        "eqbal_ratio_mean_short": 1.0,
        "eqbal_ratio_min_long": 0.8096795683892465,
        "eqbal_ratio_min_short": NaN,
        "eqbal_ratio_std_long": 0.015948453294179533,
        "eqbal_ratio_std_short": 0.0,
        "equity_balance_ratio_mean_long": 0.9966271254819918,
        "equity_balance_ratio_mean_short": 1.0,
        "equity_balance_ratio_std_long": 0.015948453294179533,
        "equity_balance_ratio_std_short": 0.0,
        "exchange": "bybit",
        "exposure_ratios_mean_long": 0.06548323793501097,
        "exposure_ratios_mean_short": 0.0,
        "fee_sum_long": -41.100298484,
        "fee_sum_short": 0,
        "final_balance_long": 2274.7250815159937,
        "final_balance_short": 1000.0,
        "final_equity_long": 2274.7250815159937,
        "final_equity_short": 1000.0,
        "gain_long": 1.2747250815159936,
        "gain_short": 0.0,
        "hrs_stuck_avg_long": 3.371429268530718,
        "hrs_stuck_avg_short": NaN,
        "hrs_stuck_max_long": 391.45,
        "hrs_stuck_max_short": NaN,
        "loss_profit_ratio_long": 0.0,
        "loss_profit_ratio_short": 1.0,
        "loss_sum_long": 0.0,
        "loss_sum_short": 0,
        "n_closes_long": 5233,
        "n_closes_short": 0,
        "n_days": 961.6666666666666,
        "n_entries_long": 1599,
        "n_entries_short": 0,
        "n_fills_long": 6832,
        "n_fills_short": 0,
        "n_ientries_long": 968,
        "n_ientries_short": 0,
        "n_normal_closes_long": 5233,
        "n_normal_closes_short": 0,
        "n_rentries_long": 631,
        "n_rentries_short": 0,
        "n_unstuck_closes_long": 0,
        "n_unstuck_closes_short": 0,
        "n_unstuck_entries_long": 0,
        "n_unstuck_entries_short": 0,
        "net_pnl_plus_fees_long": 1274.7250815160003,
        "net_pnl_plus_fees_short": 0,
        "pa_distance_1pct_worst_mean_long": 0.15597859030385247,
        "pa_distance_1pct_worst_mean_short": 100.0,
        "pa_distance_max_long": 0.23503978746567167,
        "pa_distance_max_short": 100.0,
        "pa_distance_mean_long": 0.022451202026715897,
        "pa_distance_mean_short": 100.0,
        "pa_distance_std_long": 0.028813904269279142,
        "pa_distance_std_short": 1.0,
        "pnl_sum_long": 1315.8253800000002,
        "pnl_sum_short": 0,
        "profit_sum_long": 1315.8253800000002,
        "profit_sum_short": 0,
        "sharpe_ratio_long": 0.13327102518387474,
        "sharpe_ratio_short": 0.0,
        "starting_balance": 1000.0,
        "symbol": "HBARUSDT",
        "time_at_max_exposure_long": 0.013257657813786232,
        "time_at_max_exposure_short": 0.0,
        "volume_quote_long": 311641.73750129185,
        "volume_quote_short": 0
    }
}