{
    "market_type": "futures",
    "user": "bybit_readonly",
    "symbols": [
        "TRXUSDT"
    ],
    "latency_simulation_ms": 1000,
    "starting_balance": 1000.0,
    "start_date": "2023-03-22",
    "end_date": "2024-03-21",
    "slim_analysis": true,
    "base_dir": "/home/user/passivbot/backtests/pbgui",
    "ohlcv": true,
    "adg_n_subdivisions": 10,
    "enable_interactive_plot": true,
    "plot_theme": "light",
    "plot_candles_interval": "1m",
    "spot": false,
    "exchange": "bybit",
    "session_name": "2023-03-22_2024-03-21",
    "symbol": "TRXUSDT",
    "caches_dirpath": "/home/user/passivbot/backtests/pbgui/bybit/TRXUSDT/caches/",
    "plots_dirpath": "/home/user/passivbot/backtests/pbgui/bybit/TRXUSDT/plots/2024-03-26T072604/",
    "c_mult": 1.0,
    "hedge_mode": true,
    "inverse": false,
    "maker_fee": 0.0002,
    "min_cost": 0.0,
    "min_qty": 1.0,
    "price_step": 1e-05,
    "qty_step": 1.0,
    "taker_fee": 0.00055,
    "n_parts": null,
    "config_name": "recursive_grid_1_symbols_365days",
    "logging_level": 0,
    "long": {
        "auto_unstuck_delay_minutes": 1202.6708566852437,
        "auto_unstuck_ema_dist": 0.0045906719105616774,
        "auto_unstuck_qty_pct": 0.01,
        "auto_unstuck_wallet_exposure_threshold": 0.14070087648893304,
        "backwards_tp": true,
        "ddown_factor": 0.16714051632051136,
        "ema_span_0": 342.62470709260236,
        "ema_span_1": 1402.410359483772,
        "enabled": true,
        "initial_eprice_ema_dist": -0.007096996760768014,
        "initial_qty_pct": 0.047477245062645966,
        "markup_range": 0.013612136081428824,
        "min_markup": 0.006454025098425245,
        "n_close_orders": 2,
        "rentry_pprice_dist": 0.01886779871353464,
        "rentry_pprice_dist_wallet_exposure_weighting": 1.2338369101114048,
        "wallet_exposure_limit": 1
    },
    "short": {
        "auto_unstuck_delay_minutes": 0.0,
        "auto_unstuck_ema_dist": 0.0,
        "auto_unstuck_qty_pct": 0.0,
        "auto_unstuck_wallet_exposure_threshold": 0.0,
        "backwards_tp": true,
        "ddown_factor": 1.413887351466984,
        "ema_span_0": 433.0743380738533,
        "ema_span_1": 691.0451746067787,
        "enabled": false,
        "initial_eprice_ema_dist": -0.0044142050008561615,
        "initial_qty_pct": 0.019217773838212222,
        "markup_range": 0.0008296123836580605,
        "min_markup": 0.005904530079372635,
        "n_close_orders": 9,
        "rentry_pprice_dist": 0.006273075976558335,
        "rentry_pprice_dist_wallet_exposure_weighting": 4.242302030029977,
        "wallet_exposure_limit": 1.0
    },
    "disable_plotting": true,
    "passivbot_mode": "recursive_grid",
    "n_days": 365.0,
    "result": {
        "adg_long": 0.0006639239716361711,
        "adg_per_exposure_long": 0.0006639239716361711,
        "adg_per_exposure_short": 0.0,
        "adg_short": 0.0,
        "adg_weighted_long": 0.0006983002914136005,
        "adg_weighted_per_exposure_long": 0.0006983002914136005,
        "adg_weighted_per_exposure_short": 0.0,
        "adg_weighted_short": 0.0,
        "avg_fills_per_day_long": 1.2083571183925106,
        "avg_fills_per_day_short": 0.0,
        "closest_bkr_long": 0.9533563216405151,
        "closest_bkr_short": 1.0,
        "drawdown_1pct_worst_mean_long": 0.09961348399485083,
        "drawdown_1pct_worst_mean_short": -0.0,
        "drawdown_max_long": 0.14616504242185277,
        "drawdown_max_short": -0.0,
        "eqbal_ratio_mean_long": 0.992941431135336,
        "eqbal_ratio_mean_of_10_worst_long": 0.8731637185580505,
        "eqbal_ratio_mean_of_10_worst_short": 1.0,
        "eqbal_ratio_mean_short": 1.0,
        "eqbal_ratio_min_long": 0.8542893835988352,
        "eqbal_ratio_min_short": NaN,
        "eqbal_ratio_std_long": 0.017637817519390416,
        "eqbal_ratio_std_short": 0.0,
        "equity_balance_ratio_mean_long": 0.992941431135336,
        "equity_balance_ratio_mean_short": 1.0,
        "equity_balance_ratio_std_long": 0.017637817519390416,
        "equity_balance_ratio_std_short": 0.0,
        "exchange": "bybit",
        "exposure_ratios_mean_long": 0.29388456196120355,
        "exposure_ratios_mean_short": 0.0,
        "fee_sum_long": -7.067324314,
        "fee_sum_short": 0,
        "final_balance_long": 1274.079791425848,
        "final_balance_short": 1000.0,
        "final_equity_long": 1197.7755056860008,
        "final_equity_short": 1000.0,
        "gain_long": 0.27407979142584815,
        "gain_short": 0.0,
        "hrs_stuck_avg_long": 19.818295454545456,
        "hrs_stuck_avg_short": NaN,
        "hrs_stuck_max_long": 176.21666666666667,
        "hrs_stuck_max_short": NaN,
        "loss_profit_ratio_long": 0.052518682358091553,
        "loss_profit_ratio_short": 1.0,
        "loss_sum_long": -15.583923178752485,
        "loss_sum_short": 0,
        "n_closes_long": 141,
        "n_closes_short": 0,
        "n_days": 364.9583333333333,
        "n_entries_long": 300,
        "n_entries_short": 0,
        "n_fills_long": 441,
        "n_fills_short": 0,
        "n_ientries_long": 94,
        "n_ientries_short": 0,
        "n_normal_closes_long": 103,
        "n_normal_closes_short": 0,
        "n_rentries_long": 206,
        "n_rentries_short": 0,
        "n_unstuck_closes_long": 38,
        "n_unstuck_closes_short": 0,
        "n_unstuck_entries_long": 0,
        "n_unstuck_entries_short": 0,
        "net_pnl_plus_fees_long": 274.0797914258481,
        "net_pnl_plus_fees_short": 0,
        "pa_distance_1pct_worst_mean_long": 0.10784463032933367,
        "pa_distance_1pct_worst_mean_short": 100.0,
        "pa_distance_max_long": 0.17055550610054063,
        "pa_distance_max_short": 100.0,
        "pa_distance_mean_long": 0.013396303560250305,
        "pa_distance_mean_short": 100.0,
        "pa_distance_std_long": 0.017736142667057496,
        "pa_distance_std_short": 1.0,
        "pnl_sum_long": 281.1471157398481,
        "pnl_sum_short": 0,
        "profit_sum_long": 296.7310389186006,
        "profit_sum_short": 0,
        "sharpe_ratio_long": 0.053587238245547106,
        "sharpe_ratio_short": 0.0,
        "starting_balance": 1000.0,
        "symbol": "TRXUSDT",
        "time_at_max_exposure_long": 0.17568493150684933,
        "time_at_max_exposure_short": 0.0,
        "volume_quote_long": 128775.10424015459,
        "volume_quote_short": 0
    }
}