{"config_name": "recursive_grid_10000LADYSUSDT_323days",
 "logging_level": 0,
 "long": {"auto_unstuck_delay_minutes": 521.2639513406729,
          "auto_unstuck_ema_dist": 0.014840346902231127,
          "auto_unstuck_qty_pct": 0.01,
          "auto_unstuck_wallet_exposure_threshold": 0.09309416551877753,
          "backwards_tp": false,
          "ddown_factor": 1.8030358861125002,
          "ema_span_0": 846.8604366481377,
          "ema_span_1": 994.3113371519269,
          "enabled": true,
          "initial_eprice_ema_dist": 0.005900729820436656,
          "initial_qty_pct": 0.05,
          "markup_range": 0.032102964123293325,
          "min_markup": 0.0038640537710380087,
          "n_close_orders": 6,
          "rentry_pprice_dist": 0.044894812974871225,
          "rentry_pprice_dist_wallet_exposure_weighting": 1.1103731093321818,
          "wallet_exposure_limit": 1},
 "short": {"auto_unstuck_delay_minutes": 634.3672383022922,
           "auto_unstuck_ema_dist": -0.06124614386677884,
           "auto_unstuck_qty_pct": 0.0927314520575325,
           "auto_unstuck_wallet_exposure_threshold": 0.41754180492299453,
           "backwards_tp": true,
           "ddown_factor": 1.09930420872021,
           "ema_span_0": 1166.3319568953434,
           "ema_span_1": 45.87449953742193,
           "enabled": false,
           "initial_eprice_ema_dist": -0.030776934576607407,
           "initial_qty_pct": 0.048261776731881596,
           "markup_range": 0.044037888902750254,
           "min_markup": 0.005071096764071709,
           "n_close_orders": 3,
           "rentry_pprice_dist": 0.041678074159089,
           "rentry_pprice_dist_wallet_exposure_weighting": 9.017172878079197,
           "wallet_exposure_limit": 1.0}}