{"config_name": "recursive_grid_SHIB1000USDT_365days",
 "logging_level": 0,
 "long": {"auto_unstuck_delay_minutes": 172.22199114514618,
          "auto_unstuck_ema_dist": 0.0702776545418724,
          "auto_unstuck_qty_pct": 0.07252019185082673,
          "auto_unstuck_wallet_exposure_threshold": 0.507027619658865,
          "backwards_tp": false,
          "ddown_factor": 2.890693546096197,
          "ema_span_0": 107.25417379820638,
          "ema_span_1": 573.3517198361213,
          "enabled": true,
          "initial_eprice_ema_dist": -0.0312896361371785,
          "initial_qty_pct": 0.04232322900624233,
          "markup_range": 0.002772235346264358,
          "min_markup": 0.011980333747219,
          "n_close_orders": 5,
          "rentry_pprice_dist": 0.02356396280699249,
          "rentry_pprice_dist_wallet_exposure_weighting": 4.833425984121739,
          "wallet_exposure_limit": 1.0},
 "short": {"auto_unstuck_delay_minutes": 1133.1297954879176,
           "auto_unstuck_ema_dist": -0.045309527641562104,
           "auto_unstuck_qty_pct": 0.020872239603318788,
           "auto_unstuck_wallet_exposure_threshold": 0.19990550038472576,
           "backwards_tp": false,
           "ddown_factor": 2.079964865054214,
           "ema_span_0": 586.2030279428137,
           "ema_span_1": 859.2492752833328,
           "enabled": false,
           "initial_eprice_ema_dist": -0.009398942507850313,
           "initial_qty_pct": 0.01263391530830645,
           "markup_range": 0.006050981817544396,
           "min_markup": 0.010508345268399763,
           "n_close_orders": 15,
           "rentry_pprice_dist": 0.05739924836933672,
           "rentry_pprice_dist_wallet_exposure_weighting": 5.558051410136325,
           "wallet_exposure_limit": 1.0}}