{
    "market_type": "futures",
    "user": "bybit_readonly",
    "symbols": [
        "AIUSDT"
    ],
    "latency_simulation_ms": 1000,
    "starting_balance": 1000.0,
    "start_date": "2023-01-01",
    "end_date": "2024-03-30",
    "slim_analysis": false,
    "base_dir": "/home/user/passivbot/backtests/pbgui",
    "ohlcv": true,
    "adg_n_subdivisions": 10,
    "enable_interactive_plot": "False",
    "plot_theme": "light",
    "plot_candles_interval": "1m",
    "spot": false,
    "exchange": "bybit",
    "session_name": "2023-01-01_2024-03-30",
    "symbol": "AIUSDT",
    "caches_dirpath": "/home/user/passivbot/backtests/pbgui/bybit/AIUSDT/caches/",
    "plots_dirpath": "/home/user/passivbot/backtests/pbgui/bybit/AIUSDT/plots/2024-04-06T084821/",
    "c_mult": 1.0,
    "hedge_mode": true,
    "inverse": false,
    "maker_fee": 0.0002,
    "min_cost": 0.0,
    "min_qty": 0.1,
    "price_step": 0.0001,
    "qty_step": 0.1,
    "taker_fee": 0.00055,
    "n_parts": null,
    "config_name": "recursive_grid_1_symbols_454days",
    "logging_level": 0,
    "long": {
        "auto_unstuck_delay_minutes": 1297.145103497297,
        "auto_unstuck_ema_dist": -0.015805204899480663,
        "auto_unstuck_qty_pct": 0.01,
        "auto_unstuck_wallet_exposure_threshold": 0.05820293975176088,
        "backwards_tp": false,
        "ddown_factor": 1.9619714011805005,
        "ema_span_0": 1440,
        "ema_span_1": 1130.411779922626,
        "enabled": true,
        "initial_eprice_ema_dist": 0.002976588300353364,
        "initial_qty_pct": 0.05,
        "markup_range": 0.04810516572088823,
        "min_markup": 0.005010717694293707,
        "n_close_orders": 6,
        "rentry_pprice_dist": 0.02066911000621002,
        "rentry_pprice_dist_wallet_exposure_weighting": 0.9403124172085198,
        "wallet_exposure_limit": 1
    },
    "short": {
        "auto_unstuck_delay_minutes": 1176.6570766117522,
        "auto_unstuck_ema_dist": -0.0014505160565270875,
        "auto_unstuck_qty_pct": 0.044521722806834974,
        "auto_unstuck_wallet_exposure_threshold": 0.7401808161778829,
        "backwards_tp": true,
        "ddown_factor": 1.0137952547206843,
        "ema_span_0": 1345.893681718886,
        "ema_span_1": 343.218699935223,
        "enabled": false,
        "initial_eprice_ema_dist": -0.049561086369386165,
        "initial_qty_pct": 0.036051888592702974,
        "markup_range": 0.02572823574944524,
        "min_markup": 0.004319277882384419,
        "n_close_orders": 8,
        "rentry_pprice_dist": 0.016578885104243584,
        "rentry_pprice_dist_wallet_exposure_weighting": 9.45185180470046,
        "wallet_exposure_limit": 1.0
    },
    "disable_plotting": true,
    "passivbot_mode": "recursive_grid",
    "n_days": 72.6,
    "result": {
        "adg_long": 0.013738948254923944,
        "adg_per_exposure_long": 0.013738948254923944,
        "adg_per_exposure_short": 0.0,
        "adg_short": 0.0,
        "adg_weighted_long": 0.013844790319635059,
        "adg_weighted_per_exposure_long": 0.013844790319635059,
        "adg_weighted_per_exposure_short": 0.0,
        "adg_weighted_short": 0.0,
        "avg_fills_per_day_long": 88.42250287026407,
        "avg_fills_per_day_short": 0.0,
        "closest_bkr_long": 0.9573134808232613,
        "closest_bkr_short": 1.0,
        "drawdown_1pct_worst_mean_long": 0.06913357817621528,
        "drawdown_1pct_worst_mean_short": -0.0,
        "drawdown_max_long": 0.09463392024590873,
        "drawdown_max_short": -0.0,
        "eqbal_ratio_mean_long": 0.9973361874626739,
        "eqbal_ratio_mean_of_10_worst_long": 0.9231612798334075,
        "eqbal_ratio_mean_of_10_worst_short": 1.0,
        "eqbal_ratio_mean_short": 1.0,
        "eqbal_ratio_min_long": 0.9058919751722642,
        "eqbal_ratio_min_short": NaN,
        "eqbal_ratio_std_long": 0.010481284520954296,
        "eqbal_ratio_std_short": 0.0,
        "equity_balance_ratio_mean_long": 0.9973361874626739,
        "equity_balance_ratio_mean_short": 1.0,
        "equity_balance_ratio_std_long": 0.010481284520954296,
        "equity_balance_ratio_std_short": 0.0,
        "exchange": "bybit",
        "exposure_ratios_mean_long": 0.1501715707471347,
        "exposure_ratios_mean_short": 0.0,
        "fee_sum_long": -63.977701266,
        "fee_sum_short": 0,
        "final_balance_long": 2692.3930238668413,
        "final_balance_short": 1000.0,
        "final_equity_long": 2693.664854310008,
        "final_equity_short": 1000.0,
        "gain_long": 1.6923930238668414,
        "gain_short": 0.0,
        "hrs_stuck_avg_long": 0.2678016726403823,
        "hrs_stuck_avg_short": NaN,
        "hrs_stuck_max_long": 39.916666666666664,
        "hrs_stuck_max_short": NaN,
        "loss_profit_ratio_long": 0.0011317034997606302,
        "loss_profit_ratio_short": 1.0,
        "loss_sum_long": -1.9901576447769491,
        "loss_sum_short": 0,
        "n_closes_long": 5356,
        "n_closes_short": 0,
        "n_days": 72.58333333333333,
        "n_entries_long": 1062,
        "n_entries_short": 0,
        "n_fills_long": 6418,
        "n_fills_short": 0,
        "n_ientries_long": 833,
        "n_ientries_short": 0,
        "n_normal_closes_long": 5348,
        "n_normal_closes_short": 0,
        "n_rentries_long": 229,
        "n_rentries_short": 0,
        "n_unstuck_closes_long": 8,
        "n_unstuck_closes_short": 0,
        "n_unstuck_entries_long": 0,
        "n_unstuck_entries_short": 0,
        "net_pnl_plus_fees_long": 1692.5825433791276,
        "net_pnl_plus_fees_short": 0,
        "pa_distance_1pct_worst_mean_long": 0.07312144239846406,
        "pa_distance_1pct_worst_mean_short": 100.0,
        "pa_distance_max_long": 0.10080149137841751,
        "pa_distance_max_short": 100.0,
        "pa_distance_mean_long": 0.012435291921032262,
        "pa_distance_mean_short": 100.0,
        "pa_distance_std_long": 0.013019590321596568,
        "pa_distance_std_short": 1.0,
        "pnl_sum_long": 1756.5602446451276,
        "pnl_sum_short": 0,
        "profit_sum_long": 1758.5504022899045,
        "profit_sum_short": 0,
        "sharpe_ratio_long": 0.5892062465013368,
        "sharpe_ratio_short": 0.0,
        "starting_balance": 1000.0,
        "symbol": "AIUSDT",
        "time_at_max_exposure_long": 0.09409064830751578,
        "time_at_max_exposure_short": 0.0,
        "volume_quote_long": 959821.7491825263,
        "volume_quote_short": 0
    }
}