{
    "market_type": "futures",
    "user": "bybit_readonly",
    "symbols": [
        "ARBUSDT"
    ],
    "latency_simulation_ms": 1000,
    "starting_balance": 1000.0,
    "start_date": "2020-07-30",
    "end_date": "2024-07-29",
    "slim_analysis": true,
    "base_dir": "/home/user/passivbot/backtests/pbgui",
    "ohlcv": true,
    "adg_n_subdivisions": 10,
    "enable_interactive_plot": false,
    "plot_theme": "light",
    "plot_candles_interval": "1m",
    "spot": false,
    "exchange": "bybit",
    "session_name": "2020-07-30_2024-07-29",
    "symbol": "ARBUSDT",
    "caches_dirpath": "/home/user/passivbot/backtests/pbgui/bybit/ARBUSDT/caches/",
    "plots_dirpath": "/home/user/passivbot/backtests/pbgui/bybit/ARBUSDT/plots/2024-08-04T055307/",
    "c_mult": 1.0,
    "hedge_mode": true,
    "inverse": false,
    "maker_fee": 0.0002,
    "min_cost": 0.0,
    "min_qty": 0.1,
    "price_step": 0.0001,
    "qty_step": 0.1,
    "taker_fee": 0.00055,
    "n_parts": null,
    "config_name": "recursive_grid_1_symbols_1460days",
    "logging_level": 0,
    "long": {
        "auto_unstuck_delay_minutes": 0,
        "auto_unstuck_ema_dist": 0,
        "auto_unstuck_qty_pct": 0.0,
        "auto_unstuck_wallet_exposure_threshold": 0.0,
        "backwards_tp": false,
        "ddown_factor": 0.552201769401106,
        "ema_span_0": 1020.6082180487277,
        "ema_span_1": 1437.3269127419485,
        "enabled": true,
        "initial_eprice_ema_dist": 0.0326865778409197,
        "initial_qty_pct": 0.04,
        "markup_range": 0.037483378880743774,
        "min_markup": 0.03,
        "n_close_orders": 4,
        "rentry_pprice_dist": 0.02178102415060917,
        "rentry_pprice_dist_wallet_exposure_weighting": 11.339920165977805,
        "wallet_exposure_limit": 1
    },
    "short": {
        "auto_unstuck_delay_minutes": 468.00732530853304,
        "auto_unstuck_ema_dist": -0.07055373026885388,
        "auto_unstuck_qty_pct": 0.04449410794714512,
        "auto_unstuck_wallet_exposure_threshold": 0.7093802231136672,
        "backwards_tp": false,
        "ddown_factor": 2.1185642311513675,
        "ema_span_0": 465.44535186973013,
        "ema_span_1": 622.7284484385733,
        "enabled": false,
        "initial_eprice_ema_dist": -0.043565599887610586,
        "initial_qty_pct": 0.03597119427130166,
        "markup_range": 0.053002374387515004,
        "min_markup": 0.008499697237201936,
        "n_close_orders": 7,
        "rentry_pprice_dist": 0.01823317803373729,
        "rentry_pprice_dist_wallet_exposure_weighting": 14.599969832550757,
        "wallet_exposure_limit": 1.0
    },
    "disable_plotting": true,
    "passivbot_mode": "recursive_grid",
    "n_days": 493.4,
    "result": {
        "adg_long": 0.0012705026392536567,
        "adg_per_exposure_long": 0.0012705026392536567,
        "adg_per_exposure_short": 0.0,
        "adg_short": 0.0,
        "adg_weighted_long": 0.0012905095381980035,
        "adg_weighted_per_exposure_long": 0.0012905095381980035,
        "adg_weighted_per_exposure_short": 0.0,
        "adg_weighted_short": 0.0,
        "avg_fills_per_day_long": 5.689384342538637,
        "avg_fills_per_day_short": 0.0,
        "closest_bkr_long": 0.9998778570551078,
        "closest_bkr_short": 1.0,
        "drawdown_1pct_worst_mean_long": 0.05503789353170641,
        "drawdown_1pct_worst_mean_short": -0.0,
        "drawdown_max_long": 0.21122675434643964,
        "drawdown_max_short": -0.0,
        "eqbal_ratio_mean_long": 0.9982216431419291,
        "eqbal_ratio_mean_of_10_worst_long": 0.8619599502641719,
        "eqbal_ratio_mean_of_10_worst_short": 1.0,
        "eqbal_ratio_mean_short": 1.0,
        "eqbal_ratio_min_long": 0.7799821841073357,
        "eqbal_ratio_min_short": NaN,
        "eqbal_ratio_std_long": 0.00725468814227012,
        "eqbal_ratio_std_short": 0.0,
        "equity_balance_ratio_mean_long": 0.9982216431419291,
        "equity_balance_ratio_mean_short": 1.0,
        "equity_balance_ratio_std_long": 0.00725468814227012,
        "equity_balance_ratio_std_short": 0.0,
        "exchange": "bybit",
        "exposure_ratios_mean_long": 0.07698330308989776,
        "exposure_ratios_mean_short": 0.0,
        "fee_sum_long": -10.283184524,
        "fee_sum_short": 0,
        "final_balance_long": 1870.931395475997,
        "final_balance_short": 1000.0,
        "final_equity_long": 1870.931395475997,
        "final_equity_short": 1000.0,
        "gain_long": 0.8709313954759972,
        "gain_short": 0.0,
        "hrs_stuck_avg_long": 4.199619862200048,
        "hrs_stuck_avg_short": NaN,
        "hrs_stuck_max_long": 249.78333333333333,
        "hrs_stuck_max_short": NaN,
        "loss_profit_ratio_long": 0.0,
        "loss_profit_ratio_short": 1.0,
        "loss_sum_long": 0.0,
        "loss_sum_short": 0,
        "n_closes_long": 2456,
        "n_closes_short": 0,
        "n_days": 493.375,
        "n_entries_long": 351,
        "n_entries_short": 0,
        "n_fills_long": 2807,
        "n_fills_short": 0,
        "n_ientries_long": 157,
        "n_ientries_short": 0,
        "n_normal_closes_long": 2456,
        "n_normal_closes_short": 0,
        "n_rentries_long": 194,
        "n_rentries_short": 0,
        "n_unstuck_closes_long": 0,
        "n_unstuck_closes_short": 0,
        "n_unstuck_entries_long": 0,
        "n_unstuck_entries_short": 0,
        "net_pnl_plus_fees_long": 870.9313954759998,
        "net_pnl_plus_fees_short": 0,
        "pa_distance_1pct_worst_mean_long": 0.08973715140319923,
        "pa_distance_1pct_worst_mean_short": 100.0,
        "pa_distance_max_long": 0.26607510826323016,
        "pa_distance_max_short": 100.0,
        "pa_distance_mean_long": 0.01991377767670341,
        "pa_distance_mean_short": 100.0,
        "pa_distance_std_long": 0.018584690110619896,
        "pa_distance_std_short": 1.0,
        "pnl_sum_long": 881.2145799999998,
        "pnl_sum_short": 0,
        "profit_sum_long": 881.2145799999998,
        "profit_sum_short": 0,
        "sharpe_ratio_long": 0.1320453191407604,
        "sharpe_ratio_short": 0.0,
        "starting_balance": 1000.0,
        "symbol": "ARBUSDT",
        "time_at_max_exposure_long": 0.005066711704104036,
        "time_at_max_exposure_short": 0.0,
        "volume_quote_long": 122226.85038127558,
        "volume_quote_short": 0
    }
}