{
    "market_type": "futures",
    "user": "bybit_readonly",
    "symbols": [
        "UNIUSDT"
    ],
    "latency_simulation_ms": 1000,
    "starting_balance": 1000.0,
    "start_date": "2023-03-01",
    "end_date": "2024-03-01",
    "slim_analysis": true,
    "base_dir": "/home/user/passivbot/backtests/pbgui",
    "ohlcv": true,
    "adg_n_subdivisions": 10,
    "enable_interactive_plot": true,
    "plot_theme": "light",
    "plot_candles_interval": "1m",
    "spot": false,
    "exchange": "bybit",
    "session_name": "2023-03-01_2024-03-01",
    "symbol": "UNIUSDT",
    "caches_dirpath": "/home/user/passivbot/backtests/pbgui/bybit/UNIUSDT/caches/",
    "plots_dirpath": "/home/user/passivbot/backtests/pbgui/bybit/UNIUSDT/plots/2024-03-05T084611/",
    "c_mult": 1.0,
    "hedge_mode": true,
    "inverse": false,
    "maker_fee": 0.0002,
    "min_cost": 0.0,
    "min_qty": 0.1,
    "price_step": 0.001,
    "qty_step": 0.1,
    "taker_fee": 0.00055,
    "n_parts": null,
    "config_name": "recursive_grid_1_symbols_366days",
    "logging_level": 0,
    "long": {
        "auto_unstuck_delay_minutes": 107.34900805680724,
        "auto_unstuck_ema_dist": -0.013161050343754978,
        "auto_unstuck_qty_pct": 0.08800255707411883,
        "auto_unstuck_wallet_exposure_threshold": 0.18397593138657753,
        "backwards_tp": false,
        "ddown_factor": 0.1,
        "ema_span_0": 1020.7387551905572,
        "ema_span_1": 1027.0802403324706,
        "enabled": true,
        "initial_eprice_ema_dist": -0.002964043811014769,
        "initial_qty_pct": 0.03,
        "markup_range": 0.016581780919629033,
        "min_markup": 0.014764094784386582,
        "n_close_orders": 3,
        "rentry_pprice_dist": 0.042644833921281704,
        "rentry_pprice_dist_wallet_exposure_weighting": 0.5842727617065351,
        "wallet_exposure_limit": 1
    },
    "short": {
        "auto_unstuck_delay_minutes": 0.0,
        "auto_unstuck_ema_dist": 0.0,
        "auto_unstuck_qty_pct": 0.0,
        "auto_unstuck_wallet_exposure_threshold": 0.0,
        "backwards_tp": false,
        "ddown_factor": 1.9246251798642953,
        "ema_span_0": 947.2059735149347,
        "ema_span_1": 970.214444775277,
        "enabled": false,
        "initial_eprice_ema_dist": -0.004657911110290077,
        "initial_qty_pct": 0.01935043196507685,
        "markup_range": 0.0064884656915623245,
        "min_markup": 0.004216010249844819,
        "n_close_orders": 10,
        "rentry_pprice_dist": 0.048910998906914235,
        "rentry_pprice_dist_wallet_exposure_weighting": 1.6844263487978144,
        "wallet_exposure_limit": 1.0
    },
    "disable_plotting": true,
    "passivbot_mode": "recursive_grid",
    "n_days": 366.0,
    "result": {
        "adg_long": 0.0006405549587060744,
        "adg_per_exposure_long": 0.0006405549587060744,
        "adg_per_exposure_short": 0.0,
        "adg_short": 0.0,
        "adg_weighted_long": 0.0011148638722434212,
        "adg_weighted_per_exposure_long": 0.0011148638722434212,
        "adg_weighted_per_exposure_short": 0.0,
        "adg_weighted_short": 0.0,
        "avg_fills_per_day_long": 7.634748946829102,
        "avg_fills_per_day_short": 0.0,
        "closest_bkr_long": 0.9947848710560303,
        "closest_bkr_short": 1.0,
        "drawdown_1pct_worst_mean_long": 0.08728526931121583,
        "drawdown_1pct_worst_mean_short": -0.0,
        "drawdown_max_long": 0.11552243973352568,
        "drawdown_max_short": -0.0,
        "eqbal_ratio_mean_long": 0.9980652022313173,
        "eqbal_ratio_mean_of_10_worst_long": 0.9350237804227669,
        "eqbal_ratio_mean_of_10_worst_short": 1.0,
        "eqbal_ratio_mean_short": 1.0,
        "eqbal_ratio_min_long": 0.9097883533900815,
        "eqbal_ratio_min_short": NaN,
        "eqbal_ratio_std_long": 0.005952378590360962,
        "eqbal_ratio_std_short": 0.0,
        "equity_balance_ratio_mean_long": 0.9980652022313173,
        "equity_balance_ratio_mean_short": 1.0,
        "equity_balance_ratio_std_long": 0.005952378590360962,
        "equity_balance_ratio_std_short": 0.0,
        "exchange": "bybit",
        "exposure_ratios_mean_long": 0.08716077691454503,
        "exposure_ratios_mean_short": 0.0,
        "fee_sum_long": -9.055952659999999,
        "fee_sum_short": 0,
        "final_balance_long": 1264.0759473399935,
        "final_balance_short": 1000.0,
        "final_equity_long": 1263.3677473399935,
        "final_equity_short": 1000.0,
        "gain_long": 0.2640759473399934,
        "gain_short": 0.0,
        "hrs_stuck_avg_long": 3.137480606277599,
        "hrs_stuck_avg_short": NaN,
        "hrs_stuck_max_long": 141.03333333333333,
        "hrs_stuck_max_short": NaN,
        "loss_profit_ratio_long": 0.2373983903092596,
        "loss_profit_ratio_short": 1.0,
        "loss_sum_long": -85.02614284856367,
        "loss_sum_short": 0,
        "n_closes_long": 2128,
        "n_closes_short": 0,
        "n_days": 365.9583333333333,
        "n_entries_long": 666,
        "n_entries_short": 0,
        "n_fills_long": 2794,
        "n_fills_short": 0,
        "n_ientries_long": 311,
        "n_ientries_short": 0,
        "n_normal_closes_long": 2109,
        "n_normal_closes_short": 0,
        "n_rentries_long": 355,
        "n_rentries_short": 0,
        "n_unstuck_closes_long": 19,
        "n_unstuck_closes_short": 0,
        "n_unstuck_entries_long": 0,
        "n_unstuck_entries_short": 0,
        "net_pnl_plus_fees_long": 264.07594733999923,
        "net_pnl_plus_fees_short": 0,
        "pa_distance_1pct_worst_mean_long": 0.0581626535439549,
        "pa_distance_1pct_worst_mean_short": 100.0,
        "pa_distance_max_long": 0.0844064945374208,
        "pa_distance_max_short": 100.0,
        "pa_distance_mean_long": 0.01543047493480768,
        "pa_distance_mean_short": 100.0,
        "pa_distance_std_long": 0.012218413473323897,
        "pa_distance_std_short": 1.0,
        "pnl_sum_long": 273.13189999999923,
        "pnl_sum_short": 0,
        "profit_sum_long": 358.1580428485629,
        "profit_sum_short": 0,
        "sharpe_ratio_long": 0.13605803320593357,
        "sharpe_ratio_short": 0.0,
        "starting_balance": 1000.0,
        "symbol": "UNIUSDT",
        "time_at_max_exposure_long": 0.004326047358834244,
        "time_at_max_exposure_short": 0.0,
        "volume_quote_long": 163617.99040347518,
        "volume_quote_short": 0
    }
}