{
    "market_type": "futures",
    "user": "bybit_readonly",
    "symbols": [
        "1000RATSUSDT"
    ],
    "latency_simulation_ms": 1000,
    "starting_balance": 1000.0,
    "start_date": "2024-01-01",
    "end_date": "2024-05-23",
    "slim_analysis": false,
    "base_dir": "/home/user/passivbot/backtests/pbgui",
    "ohlcv": true,
    "adg_n_subdivisions": 10,
    "enable_interactive_plot": "False",
    "plot_theme": "light",
    "plot_candles_interval": "1m",
    "spot": false,
    "exchange": "bybit",
    "session_name": "2024-01-01_2024-05-23",
    "symbol": "1000RATSUSDT",
    "caches_dirpath": "/home/user/passivbot/backtests/pbgui/bybit/1000RATSUSDT/caches/",
    "plots_dirpath": "/home/user/passivbot/backtests/pbgui/bybit/1000RATSUSDT/plots/2024-05-26T094337/",
    "c_mult": 1.0,
    "hedge_mode": true,
    "inverse": false,
    "maker_fee": 0.0002,
    "min_cost": 0.0,
    "min_qty": 10.0,
    "price_step": 1e-05,
    "qty_step": 10.0,
    "taker_fee": 0.00055,
    "n_parts": null,
    "config_name": "recursive_grid_1_symbols_143days",
    "logging_level": 0,
    "long": {
        "auto_unstuck_delay_minutes": 1078.0804368943614,
        "auto_unstuck_ema_dist": -0.0314304265657597,
        "auto_unstuck_qty_pct": 0.01,
        "auto_unstuck_wallet_exposure_threshold": 0.08712753156426657,
        "backwards_tp": false,
        "ddown_factor": 0.5023533624842556,
        "ema_span_0": 100,
        "ema_span_1": 119.98029568554675,
        "enabled": true,
        "initial_eprice_ema_dist": 0.01933836772244544,
        "initial_qty_pct": 0.04091720092343265,
        "markup_range": 0.045453378697267094,
        "min_markup": 0.012346032588637711,
        "n_close_orders": 4,
        "rentry_pprice_dist": 0.013903002982853175,
        "rentry_pprice_dist_wallet_exposure_weighting": 11.447732496595442,
        "wallet_exposure_limit": 1
    },
    "short": {
        "auto_unstuck_delay_minutes": 445.2203295842346,
        "auto_unstuck_ema_dist": -0.04218114817778314,
        "auto_unstuck_qty_pct": 0.08178463085296452,
        "auto_unstuck_wallet_exposure_threshold": 0.8791945205807207,
        "backwards_tp": false,
        "ddown_factor": 2.6958714806785333,
        "ema_span_0": 15.089504053173306,
        "ema_span_1": 52.90126690863757,
        "enabled": false,
        "initial_eprice_ema_dist": -0.07507872676154645,
        "initial_qty_pct": 0.02846412203552797,
        "markup_range": 0.02644290803033021,
        "min_markup": 0.009734349874189613,
        "n_close_orders": 10,
        "rentry_pprice_dist": 0.026622029670764557,
        "rentry_pprice_dist_wallet_exposure_weighting": 16.195294461316895,
        "wallet_exposure_limit": 1.0
    },
    "disable_plotting": true,
    "passivbot_mode": "recursive_grid",
    "n_days": 143.0,
    "result": {
        "adg_long": 0.00547339067349828,
        "adg_per_exposure_long": 0.00547339067349828,
        "adg_per_exposure_short": 0.0,
        "adg_short": 0.0,
        "adg_weighted_long": 0.0037009040472186115,
        "adg_weighted_per_exposure_long": 0.0037009040472186115,
        "adg_weighted_per_exposure_short": 0.0,
        "adg_weighted_short": 0.0,
        "avg_fills_per_day_long": 31.54765374526377,
        "avg_fills_per_day_short": 0.0,
        "closest_bkr_long": 0.9583674514374493,
        "closest_bkr_short": 1.0,
        "drawdown_1pct_worst_mean_long": 0.19814592732419084,
        "drawdown_1pct_worst_mean_short": -0.0,
        "drawdown_max_long": 0.22153787691478927,
        "drawdown_max_short": -0.0,
        "eqbal_ratio_mean_long": 0.9808695611644747,
        "eqbal_ratio_mean_of_10_worst_long": 0.7987661598320087,
        "eqbal_ratio_mean_of_10_worst_short": 1.0,
        "eqbal_ratio_mean_short": 1.0,
        "eqbal_ratio_min_long": 0.7845221937912574,
        "eqbal_ratio_min_short": NaN,
        "eqbal_ratio_std_long": 0.04356190991288141,
        "eqbal_ratio_std_short": 0.0,
        "equity_balance_ratio_mean_long": 0.9808695611644747,
        "equity_balance_ratio_mean_short": 1.0,
        "equity_balance_ratio_std_long": 0.04356190991288141,
        "equity_balance_ratio_std_short": 0.0,
        "exchange": "bybit",
        "exposure_ratios_mean_long": 0.23671052993880332,
        "exposure_ratios_mean_short": 0.0,
        "fee_sum_long": -28.83751,
        "fee_sum_short": 0,
        "final_balance_long": 2182.199289999988,
        "final_balance_short": 1000.0,
        "final_equity_long": 2182.199289999988,
        "final_equity_short": 1000.0,
        "gain_long": 1.1821992899999882,
        "gain_short": 0.0,
        "hrs_stuck_avg_long": 0.7598765432098765,
        "hrs_stuck_avg_short": NaN,
        "hrs_stuck_max_long": 92.16666666666667,
        "hrs_stuck_max_short": NaN,
        "loss_profit_ratio_long": 0.039573283402982225,
        "loss_profit_ratio_short": 1.0,
        "loss_sum_long": -49.899385002166056,
        "loss_sum_short": 0,
        "n_closes_long": 3626,
        "n_closes_short": 0,
        "n_days": 142.95833333333334,
        "n_entries_long": 884,
        "n_entries_short": 0,
        "n_fills_long": 4510,
        "n_fills_short": 0,
        "n_ientries_long": 403,
        "n_ientries_short": 0,
        "n_normal_closes_long": 3596,
        "n_normal_closes_short": 0,
        "n_rentries_long": 481,
        "n_rentries_short": 0,
        "n_unstuck_closes_long": 30,
        "n_unstuck_closes_short": 0,
        "n_unstuck_entries_long": 0,
        "n_unstuck_entries_short": 0,
        "net_pnl_plus_fees_long": 1182.1992900000027,
        "net_pnl_plus_fees_short": 0,
        "pa_distance_1pct_worst_mean_long": 0.2340091814048101,
        "pa_distance_1pct_worst_mean_short": 100.0,
        "pa_distance_max_long": 0.2634548990617319,
        "pa_distance_max_short": 100.0,
        "pa_distance_mean_long": 0.044498955700812595,
        "pa_distance_mean_short": 100.0,
        "pa_distance_std_long": 0.05738416059712793,
        "pa_distance_std_short": 1.0,
        "pnl_sum_long": 1211.0368000000028,
        "pnl_sum_short": 0,
        "profit_sum_long": 1260.936185002169,
        "profit_sum_short": 0,
        "sharpe_ratio_long": 0.18206289904220274,
        "sharpe_ratio_short": 0.0,
        "starting_balance": 1000.0,
        "symbol": "1000RATSUSDT",
        "time_at_max_exposure_long": 0.15675990675990675,
        "time_at_max_exposure_short": 0.0,
        "volume_quote_long": 412507.69993448583,
        "volume_quote_short": 0
    }
}