{"config_name": "recursive_grid_OCEANUSDT_454days",
 "logging_level": 0,
 "long": {"auto_unstuck_delay_minutes": 1324.4713559712754,
          "auto_unstuck_ema_dist": 0.018429711417300494,
          "auto_unstuck_qty_pct": 0.01,
          "auto_unstuck_wallet_exposure_threshold": 0.06717478805718417,
          "backwards_tp": false,
          "ddown_factor": 1.429575474856771,
          "ema_span_0": 838.9465222228091,
          "ema_span_1": 821.9826596157505,
          "enabled": true,
          "initial_eprice_ema_dist": 0.004282620000583345,
          "initial_qty_pct": 0.05,
          "markup_range": 0.05724785038878153,
          "min_markup": 0.00541706084291684,
          "n_close_orders": 4,
          "rentry_pprice_dist": 0.026576243587214974,
          "rentry_pprice_dist_wallet_exposure_weighting": 1.234188643116593,
          "wallet_exposure_limit": 1},
 "short": {"auto_unstuck_delay_minutes": 500.5712342569593,
           "auto_unstuck_ema_dist": -0.04093740167784154,
           "auto_unstuck_qty_pct": 0.022681213442373102,
           "auto_unstuck_wallet_exposure_threshold": 0.7353836875252073,
           "backwards_tp": true,
           "ddown_factor": 2.373730481276428,
           "ema_span_0": 1401.3885574642939,
           "ema_span_1": 526.2034837928253,
           "enabled": false,
           "initial_eprice_ema_dist": -0.08713774661421471,
           "initial_qty_pct": 0.023231294173998003,
           "markup_range": 0.0012242593601737761,
           "min_markup": 0.004412123291455461,
           "n_close_orders": 12,
           "rentry_pprice_dist": 0.04640516539380887,
           "rentry_pprice_dist_wallet_exposure_weighting": 19.398206482264623,
           "wallet_exposure_limit": 1.0}}