{
    "market_type": "futures",
    "user": "bybit_readonly",
    "symbols": [
        "TRXUSDT"
    ],
    "latency_simulation_ms": 1000,
    "starting_balance": 1000.0,
    "start_date": "2023-01-01",
    "end_date": "2024-03-30",
    "slim_analysis": false,
    "base_dir": "/home/user/passivbot/backtests/pbgui",
    "ohlcv": true,
    "adg_n_subdivisions": 10,
    "enable_interactive_plot": "False",
    "plot_theme": "light",
    "plot_candles_interval": "1m",
    "spot": false,
    "exchange": "bybit",
    "session_name": "2023-01-01_2024-03-30",
    "symbol": "TRXUSDT",
    "caches_dirpath": "/home/user/passivbot/backtests/pbgui/bybit/TRXUSDT/caches/",
    "plots_dirpath": "/home/user/passivbot/backtests/pbgui/bybit/TRXUSDT/plots/2024-04-09T031321/",
    "c_mult": 1.0,
    "hedge_mode": true,
    "inverse": false,
    "maker_fee": 0.0002,
    "min_cost": 0.0,
    "min_qty": 1.0,
    "price_step": 1e-05,
    "qty_step": 1.0,
    "taker_fee": 0.00055,
    "n_parts": null,
    "config_name": "recursive_grid_1_symbols_454days",
    "logging_level": 0,
    "long": {
        "auto_unstuck_delay_minutes": 534.9699597603868,
        "auto_unstuck_ema_dist": 0.003381148032124359,
        "auto_unstuck_qty_pct": 0.01,
        "auto_unstuck_wallet_exposure_threshold": 0.04367479657544013,
        "backwards_tp": false,
        "ddown_factor": 1.438559876603838,
        "ema_span_0": 596.0367076017014,
        "ema_span_1": 671.8723930639528,
        "enabled": true,
        "initial_eprice_ema_dist": 0.0002410810234984024,
        "initial_qty_pct": 0.05,
        "markup_range": 0.057623139880338896,
        "min_markup": 0.005712310759833026,
        "n_close_orders": 4,
        "rentry_pprice_dist": 0.02,
        "rentry_pprice_dist_wallet_exposure_weighting": 1.0986033256279626,
        "wallet_exposure_limit": 1
    },
    "short": {
        "auto_unstuck_delay_minutes": 680.759908607372,
        "auto_unstuck_ema_dist": -0.08807272040095668,
        "auto_unstuck_qty_pct": 0.05663301714646262,
        "auto_unstuck_wallet_exposure_threshold": 0.21258477210342816,
        "backwards_tp": true,
        "ddown_factor": 1.5242834751146785,
        "ema_span_0": 1323.3132092980484,
        "ema_span_1": 199.7778175760571,
        "enabled": false,
        "initial_eprice_ema_dist": -0.08169647507267253,
        "initial_qty_pct": 0.028263296776347854,
        "markup_range": 0.016913574966198355,
        "min_markup": 0.005037356324770874,
        "n_close_orders": 3,
        "rentry_pprice_dist": 0.005362057751376705,
        "rentry_pprice_dist_wallet_exposure_weighting": 11.016405078354627,
        "wallet_exposure_limit": 1.0
    },
    "disable_plotting": true,
    "passivbot_mode": "recursive_grid",
    "n_days": 454.0,
    "result": {
        "adg_long": 0.0008850518974274912,
        "adg_per_exposure_long": 0.0008850518974274912,
        "adg_per_exposure_short": 0.0,
        "adg_short": 0.0,
        "adg_weighted_long": 0.0011412371993881898,
        "adg_weighted_per_exposure_long": 0.0011412371993881898,
        "adg_weighted_per_exposure_short": 0.0,
        "adg_weighted_short": 0.0,
        "avg_fills_per_day_long": 9.789444699403397,
        "avg_fills_per_day_short": 0.0,
        "closest_bkr_long": 0.9566765010726698,
        "closest_bkr_short": 1.0,
        "drawdown_1pct_worst_mean_long": 0.09617271479271639,
        "drawdown_1pct_worst_mean_short": -0.0,
        "drawdown_max_long": 0.12982621321266902,
        "drawdown_max_short": -0.0,
        "eqbal_ratio_mean_long": 0.9938785215969892,
        "eqbal_ratio_mean_of_10_worst_long": 0.8835740303755497,
        "eqbal_ratio_mean_of_10_worst_short": 1.0,
        "eqbal_ratio_mean_short": 1.0,
        "eqbal_ratio_min_long": 0.873315345713993,
        "eqbal_ratio_min_short": NaN,
        "eqbal_ratio_std_long": 0.016106663135382168,
        "eqbal_ratio_std_short": 0.0,
        "equity_balance_ratio_mean_long": 0.9938785215969892,
        "equity_balance_ratio_mean_short": 1.0,
        "equity_balance_ratio_std_long": 0.016106663135382168,
        "equity_balance_ratio_std_short": 0.0,
        "exchange": "bybit",
        "exposure_ratios_mean_long": 0.2508513766287124,
        "exposure_ratios_mean_short": 0.0,
        "fee_sum_long": -25.390681866,
        "fee_sum_short": 0,
        "final_balance_long": 1494.2120222894491,
        "final_balance_short": 1000.0,
        "final_equity_long": 1493.336588133989,
        "final_equity_short": 1000.0,
        "gain_long": 0.49421202228944905,
        "gain_short": 0.0,
        "hrs_stuck_avg_long": 2.4307975091904868,
        "hrs_stuck_avg_short": NaN,
        "hrs_stuck_max_long": 137.06666666666666,
        "hrs_stuck_max_short": NaN,
        "loss_profit_ratio_long": 0.08043363655103423,
        "loss_profit_ratio_short": 1.0,
        "loss_sum_long": -45.44917769743359,
        "loss_sum_short": 0,
        "n_closes_long": 3729,
        "n_closes_short": 0,
        "n_days": 453.9583333333333,
        "n_entries_long": 715,
        "n_entries_short": 0,
        "n_fills_long": 4444,
        "n_fills_short": 0,
        "n_ientries_long": 537,
        "n_ientries_short": 0,
        "n_normal_closes_long": 3621,
        "n_normal_closes_short": 0,
        "n_rentries_long": 178,
        "n_rentries_short": 0,
        "n_unstuck_closes_long": 108,
        "n_unstuck_closes_short": 0,
        "n_unstuck_entries_long": 0,
        "n_unstuck_entries_short": 0,
        "net_pnl_plus_fees_long": 494.21202228946015,
        "net_pnl_plus_fees_short": 0,
        "pa_distance_1pct_worst_mean_long": 0.09887866318381376,
        "pa_distance_1pct_worst_mean_short": 100.0,
        "pa_distance_max_long": 0.14079798649797376,
        "pa_distance_max_short": 100.0,
        "pa_distance_mean_long": 0.012773731206439539,
        "pa_distance_mean_short": 100.0,
        "pa_distance_std_long": 0.016074877854124394,
        "pa_distance_std_short": 1.0,
        "pnl_sum_long": 519.6027041554602,
        "pnl_sum_short": 0,
        "profit_sum_long": 565.0518818528938,
        "profit_sum_short": 0,
        "sharpe_ratio_long": 0.0808515091932223,
        "sharpe_ratio_short": 0.0,
        "starting_balance": 1000.0,
        "symbol": "TRXUSDT",
        "time_at_max_exposure_long": 0.17400881057268722,
        "time_at_max_exposure_short": 0.0,
        "volume_quote_long": 426774.3077084983,
        "volume_quote_short": 0
    }
}