{
    "market_type": "futures",
    "user": "bybit_readonly",
    "symbols": [
        "BNBUSDT"
    ],
    "latency_simulation_ms": 1000,
    "starting_balance": 1000.0,
    "start_date": "2023-01-01",
    "end_date": "2024-03-30",
    "slim_analysis": false,
    "base_dir": "/home/user/passivbot/backtests/pbgui",
    "ohlcv": true,
    "adg_n_subdivisions": 10,
    "enable_interactive_plot": "False",
    "plot_theme": "light",
    "plot_candles_interval": "1m",
    "spot": false,
    "exchange": "bybit",
    "session_name": "2023-01-01_2024-03-30",
    "symbol": "BNBUSDT",
    "caches_dirpath": "/home/user/passivbot/backtests/pbgui/bybit/BNBUSDT/caches/",
    "plots_dirpath": "/home/user/passivbot/backtests/pbgui/bybit/BNBUSDT/plots/2024-04-09T134011/",
    "c_mult": 1.0,
    "hedge_mode": true,
    "inverse": false,
    "maker_fee": 0.0002,
    "min_cost": 0.0,
    "min_qty": 0.01,
    "price_step": 0.05,
    "qty_step": 0.01,
    "taker_fee": 0.00055,
    "n_parts": null,
    "config_name": "recursive_grid_1_symbols_454days",
    "logging_level": 0,
    "long": {
        "auto_unstuck_delay_minutes": 1289.1646059579878,
        "auto_unstuck_ema_dist": -0.02307640284970626,
        "auto_unstuck_qty_pct": 0.01,
        "auto_unstuck_wallet_exposure_threshold": 0.0929537271929415,
        "backwards_tp": false,
        "ddown_factor": 1.3784227908450613,
        "ema_span_0": 1030.837666647612,
        "ema_span_1": 886.844404852963,
        "enabled": true,
        "initial_eprice_ema_dist": 0.0064094039123531454,
        "initial_qty_pct": 0.05,
        "markup_range": 0.024648030644608927,
        "min_markup": 0.003035297462775567,
        "n_close_orders": 5,
        "rentry_pprice_dist": 0.029629110208115345,
        "rentry_pprice_dist_wallet_exposure_weighting": 0.8879230794769735,
        "wallet_exposure_limit": 1
    },
    "short": {
        "auto_unstuck_delay_minutes": 1202.887244841589,
        "auto_unstuck_ema_dist": -0.099645547797992,
        "auto_unstuck_qty_pct": 0.05429162361716345,
        "auto_unstuck_wallet_exposure_threshold": 0.22646160272364002,
        "backwards_tp": true,
        "ddown_factor": 1.842046274571518,
        "ema_span_0": 1244.8062847990957,
        "ema_span_1": 720.1337650906271,
        "enabled": false,
        "initial_eprice_ema_dist": -0.02251048082650868,
        "initial_qty_pct": 0.02983673629397717,
        "markup_range": 0.054248048312596366,
        "min_markup": 0.00997131143771681,
        "n_close_orders": 7,
        "rentry_pprice_dist": 0.018471757097262027,
        "rentry_pprice_dist_wallet_exposure_weighting": 13.475104174488468,
        "wallet_exposure_limit": 1.0
    },
    "disable_plotting": true,
    "passivbot_mode": "recursive_grid",
    "n_days": 454.0,
    "result": {
        "adg_long": 0.0006745187955135012,
        "adg_per_exposure_long": 0.0006745187955135012,
        "adg_per_exposure_short": 0.0,
        "adg_short": 0.0,
        "adg_weighted_long": 0.0011104636003077095,
        "adg_weighted_per_exposure_long": 0.0011104636003077095,
        "adg_weighted_per_exposure_short": 0.0,
        "adg_weighted_short": 0.0,
        "avg_fills_per_day_long": 16.30986691142726,
        "avg_fills_per_day_short": 0.0,
        "closest_bkr_long": 0.9533137623152637,
        "closest_bkr_short": 1.0,
        "drawdown_1pct_worst_mean_long": 0.04281835966459982,
        "drawdown_1pct_worst_mean_short": -0.0,
        "drawdown_max_long": 0.0779295425797501,
        "drawdown_max_short": -0.0,
        "eqbal_ratio_mean_long": 0.9990172105892887,
        "eqbal_ratio_mean_of_10_worst_long": 0.931590313385626,
        "eqbal_ratio_mean_of_10_worst_short": 1.0,
        "eqbal_ratio_mean_short": 1.0,
        "eqbal_ratio_min_long": 0.9242195608119782,
        "eqbal_ratio_min_short": NaN,
        "eqbal_ratio_std_long": 0.005079979277423072,
        "eqbal_ratio_std_short": 0.0,
        "equity_balance_ratio_mean_long": 0.9990172105892887,
        "equity_balance_ratio_mean_short": 1.0,
        "equity_balance_ratio_std_long": 0.005079979277423072,
        "equity_balance_ratio_std_short": 0.0,
        "exchange": "bybit",
        "exposure_ratios_mean_long": 0.06153594893459329,
        "exposure_ratios_mean_short": 0.0,
        "fee_sum_long": -24.564110499999998,
        "fee_sum_short": 0,
        "final_balance_long": 1358.1183894999695,
        "final_balance_short": 1000.0,
        "final_equity_long": 1358.1183894999695,
        "final_equity_short": 1000.0,
        "gain_long": 0.35811838949996955,
        "gain_short": 0.0,
        "hrs_stuck_avg_long": 1.4621549822144178,
        "hrs_stuck_avg_short": NaN,
        "hrs_stuck_max_long": 120.28333333333333,
        "hrs_stuck_max_short": NaN,
        "loss_profit_ratio_long": 0.010770969615102502,
        "loss_profit_ratio_short": 1.0,
        "loss_sum_long": -4.166741425014269,
        "loss_sum_short": 0,
        "n_closes_long": 6390,
        "n_closes_short": 0,
        "n_days": 453.9583333333333,
        "n_entries_long": 1014,
        "n_entries_short": 0,
        "n_fills_long": 7404,
        "n_fills_short": 0,
        "n_ientries_long": 873,
        "n_ientries_short": 0,
        "n_normal_closes_long": 6372,
        "n_normal_closes_short": 0,
        "n_rentries_long": 141,
        "n_rentries_short": 0,
        "n_unstuck_closes_long": 18,
        "n_unstuck_closes_short": 0,
        "n_unstuck_entries_long": 0,
        "n_unstuck_entries_short": 0,
        "net_pnl_plus_fees_long": 358.1183894999989,
        "net_pnl_plus_fees_short": 0,
        "pa_distance_1pct_worst_mean_long": 0.043286396069233984,
        "pa_distance_1pct_worst_mean_short": 100.0,
        "pa_distance_max_long": 0.07820979558133768,
        "pa_distance_max_short": 100.0,
        "pa_distance_mean_long": 0.008393005939316007,
        "pa_distance_mean_short": 100.0,
        "pa_distance_std_long": 0.008238225950342523,
        "pa_distance_std_short": 1.0,
        "pnl_sum_long": 382.6824999999989,
        "pnl_sum_short": 0,
        "profit_sum_long": 386.8492414250132,
        "profit_sum_short": 0,
        "sharpe_ratio_long": 0.15218114110732794,
        "sharpe_ratio_short": 0.0,
        "starting_balance": 1000.0,
        "symbol": "BNBUSDT",
        "time_at_max_exposure_long": 0.03313142437591777,
        "time_at_max_exposure_short": 0.0,
        "volume_quote_long": 349423.4471606856,
        "volume_quote_short": 0
    }
}