{
    "market_type": "futures",
    "user": "bybit_readonly",
    "symbols": [
        "POLYXUSDT"
    ],
    "latency_simulation_ms": 1000,
    "starting_balance": 1000.0,
    "start_date": "2023-01-01",
    "end_date": "2024-03-30",
    "slim_analysis": false,
    "base_dir": "/home/user/passivbot/backtests/pbgui",
    "ohlcv": true,
    "adg_n_subdivisions": 10,
    "enable_interactive_plot": "False",
    "plot_theme": "light",
    "plot_candles_interval": "1m",
    "spot": false,
    "exchange": "bybit",
    "session_name": "2023-01-01_2024-03-30",
    "symbol": "POLYXUSDT",
    "caches_dirpath": "/home/user/passivbot/backtests/pbgui/bybit/POLYXUSDT/caches/",
    "plots_dirpath": "/home/user/passivbot/backtests/pbgui/bybit/POLYXUSDT/plots/2024-04-04T195858/",
    "c_mult": 1.0,
    "hedge_mode": true,
    "inverse": false,
    "maker_fee": 0.0002,
    "min_cost": 0.0,
    "min_qty": 1.0,
    "price_step": 0.0001,
    "qty_step": 1.0,
    "taker_fee": 0.00055,
    "n_parts": null,
    "config_name": "recursive_grid_1_symbols_454days",
    "logging_level": 0,
    "long": {
        "auto_unstuck_delay_minutes": 946.091233205934,
        "auto_unstuck_ema_dist": 0.009380878388642364,
        "auto_unstuck_qty_pct": 0.01,
        "auto_unstuck_wallet_exposure_threshold": 0.08576599946270737,
        "backwards_tp": false,
        "ddown_factor": 0.7559805156866073,
        "ema_span_0": 990.9739191289135,
        "ema_span_1": 948.9357364198377,
        "enabled": true,
        "initial_eprice_ema_dist": 0.0037644039935946687,
        "initial_qty_pct": 0.05,
        "markup_range": 0.06,
        "min_markup": 0.01,
        "n_close_orders": 6,
        "rentry_pprice_dist": 0.052066069633853816,
        "rentry_pprice_dist_wallet_exposure_weighting": 2.5218287860746034,
        "wallet_exposure_limit": 1
    },
    "short": {
        "auto_unstuck_delay_minutes": 418.44332220844524,
        "auto_unstuck_ema_dist": -0.012401839700105402,
        "auto_unstuck_qty_pct": 0.0979157945542422,
        "auto_unstuck_wallet_exposure_threshold": 0.408503479899866,
        "backwards_tp": true,
        "ddown_factor": 1.5198128903631698,
        "ema_span_0": 971.9178842567976,
        "ema_span_1": 438.22652349777303,
        "enabled": false,
        "initial_eprice_ema_dist": -0.08200244029705937,
        "initial_qty_pct": 0.042476240236018016,
        "markup_range": 0.013966635798544272,
        "min_markup": 0.00574637694643433,
        "n_close_orders": 16,
        "rentry_pprice_dist": 0.03653878303907484,
        "rentry_pprice_dist_wallet_exposure_weighting": 2.6786664423092876,
        "wallet_exposure_limit": 1.0
    },
    "disable_plotting": true,
    "passivbot_mode": "recursive_grid",
    "n_days": 157.6,
    "result": {
        "adg_long": 0.0028609343820227284,
        "adg_per_exposure_long": 0.0028609343820227284,
        "adg_per_exposure_short": 0.0,
        "adg_short": 0.0,
        "adg_weighted_long": 0.003538866880005198,
        "adg_weighted_per_exposure_long": 0.003538866880005198,
        "adg_weighted_per_exposure_short": 0.0,
        "adg_weighted_short": 0.0,
        "avg_fills_per_day_long": 25.18032786885246,
        "avg_fills_per_day_short": 0.0,
        "closest_bkr_long": 0.9997946102676208,
        "closest_bkr_short": 1.0,
        "drawdown_1pct_worst_mean_long": 0.034990471024939365,
        "drawdown_1pct_worst_mean_short": -0.0,
        "drawdown_max_long": 0.07633019495999971,
        "drawdown_max_short": -0.0,
        "eqbal_ratio_mean_long": 0.9987757162242374,
        "eqbal_ratio_mean_of_10_worst_long": 0.9443190893493127,
        "eqbal_ratio_mean_of_10_worst_short": 1.0,
        "eqbal_ratio_mean_short": 1.0,
        "eqbal_ratio_min_long": 0.8894804966563499,
        "eqbal_ratio_min_short": NaN,
        "eqbal_ratio_std_long": 0.004199670051645636,
        "eqbal_ratio_std_short": 0.0,
        "equity_balance_ratio_mean_long": 0.9987757162242374,
        "equity_balance_ratio_mean_short": 1.0,
        "equity_balance_ratio_std_long": 0.004199670051645636,
        "equity_balance_ratio_std_short": 0.0,
        "exchange": "bybit",
        "exposure_ratios_mean_long": 0.0672863239079532,
        "exposure_ratios_mean_short": 0.0,
        "fee_sum_long": -11.936229260000001,
        "fee_sum_short": 0,
        "final_balance_long": 1568.6131707399984,
        "final_balance_short": 1000.0,
        "final_equity_long": 1545.0357707399985,
        "final_equity_short": 1000.0,
        "gain_long": 0.5686131707399984,
        "gain_short": 0.0,
        "hrs_stuck_avg_long": 0.9452777077556508,
        "hrs_stuck_avg_short": NaN,
        "hrs_stuck_max_long": 105.86666666666666,
        "hrs_stuck_max_short": NaN,
        "loss_profit_ratio_long": 2.6006045306309856e-05,
        "loss_profit_ratio_short": 1.0,
        "loss_sum_long": -0.015098186643076883,
        "loss_sum_short": 0,
        "n_closes_long": 3492,
        "n_closes_short": 0,
        "n_days": 157.58333333333334,
        "n_entries_long": 476,
        "n_entries_short": 0,
        "n_fills_long": 3968,
        "n_fills_short": 0,
        "n_ientries_long": 363,
        "n_ientries_short": 0,
        "n_normal_closes_long": 3491,
        "n_normal_closes_short": 0,
        "n_rentries_long": 113,
        "n_rentries_short": 0,
        "n_unstuck_closes_long": 1,
        "n_unstuck_closes_short": 0,
        "n_unstuck_entries_long": 0,
        "n_unstuck_entries_short": 0,
        "net_pnl_plus_fees_long": 568.6131707399999,
        "net_pnl_plus_fees_short": 0,
        "pa_distance_1pct_worst_mean_long": 0.06833289166008462,
        "pa_distance_1pct_worst_mean_short": 100.0,
        "pa_distance_max_long": 0.1117408400997759,
        "pa_distance_max_short": 100.0,
        "pa_distance_mean_long": 0.01687970593175545,
        "pa_distance_mean_short": 100.0,
        "pa_distance_std_long": 0.014037284256461509,
        "pa_distance_std_short": 1.0,
        "pnl_sum_long": 580.5493999999999,
        "pnl_sum_short": 0,
        "profit_sum_long": 580.5644981866429,
        "profit_sum_short": 0,
        "sharpe_ratio_long": 0.2663527245273291,
        "sharpe_ratio_short": 0.0,
        "starting_balance": 1000.0,
        "symbol": "POLYXUSDT",
        "time_at_max_exposure_long": 0.007401533174729051,
        "time_at_max_exposure_short": 0.0,
        "volume_quote_long": 183156.1246337289,
        "volume_quote_short": 0
    }
}