{
    "market_type": "spot",
    "user": "",
    "symbols": [
        "SOLUSDT"
    ],
    "latency_simulation_ms": 1000,
    "starting_balance": 300.0,
    "start_date": "2023-01-01",
    "end_date": "2024-01-01",
    "slim_analysis": true,
    "base_dir": "tmp/20240209_230439__w2hTO9",
    "ohlcv": true,
    "adg_n_subdivisions": 10,
    "enable_interactive_plot": false,
    "plot_theme": "light",
    "plot_candles_interval": "1m",
    "spot": true,
    "exchange": "binance",
    "session_name": "2023-01-01_2024-01-01",
    "symbol": "SOLUSDT",
    "caches_dirpath": "tmp/20240209_230439__w2hTO9/binance_spot/SOLUSDT/caches/",
    "plots_dirpath": "tmp/20240209_230439__w2hTO9/binance_spot/SOLUSDT/plots/2024-02-09T230827/",
    "c_mult": 1.0,
    "hedge_mode": false,
    "inverse": false,
    "maker_fee": 0.001,
    "min_cost": 5.0,
    "min_qty": 0.01,
    "price_step": 0.01,
    "qty_step": 0.01,
    "taker_fee": 0.001,
    "n_parts": null,
    "config_name": "recursive_grid_SOLUSDT_365days",
    "logging_level": 0,
    "long": {
        "auto_unstuck_delay_minutes": 306.2327215840678,
        "auto_unstuck_ema_dist": -0.08352385299010914,
        "auto_unstuck_qty_pct": 0.01211621593185951,
        "auto_unstuck_wallet_exposure_threshold": 0.5766650597063662,
        "backwards_tp": false,
        "ddown_factor": 1.3988088147828919,
        "ema_span_0": 79.67665857213551,
        "ema_span_1": 632.1221116136775,
        "enabled": true,
        "initial_eprice_ema_dist": -0.06701438276668993,
        "initial_qty_pct": 0.022747644627622958,
        "markup_range": 0.018301388571010074,
        "min_markup": 0.008978323269162581,
        "n_close_orders": 5,
        "rentry_pprice_dist": 0.03503073214026074,
        "rentry_pprice_dist_wallet_exposure_weighting": 0.3712961644981235,
        "wallet_exposure_limit": 1.0
    },
    "short": {
        "auto_unstuck_delay_minutes": 0.0,
        "auto_unstuck_ema_dist": 0.0,
        "auto_unstuck_qty_pct": 0.0,
        "auto_unstuck_wallet_exposure_threshold": 0.0,
        "backwards_tp": false,
        "ddown_factor": 0.0,
        "ema_span_0": 1.0,
        "ema_span_1": 1.0,
        "enabled": false,
        "initial_eprice_ema_dist": 0.0,
        "initial_qty_pct": 0.0,
        "markup_range": 0.0,
        "min_markup": 0.0,
        "n_close_orders": 1,
        "rentry_pprice_dist": 0.0,
        "rentry_pprice_dist_wallet_exposure_weighting": 0.0,
        "wallet_exposure_limit": 0.0
    },
    "do_long": true,
    "do_short": false,
    "disable_plotting": false,
    "passivbot_mode": "recursive_grid",
    "n_days": 365.0,
    "result": {
        "adg_long": 0.0013723468810533657,
        "adg_per_exposure_long": 0.0013723468810533657,
        "adg_per_exposure_short": 0.0,
        "adg_short": 0.0,
        "adg_weighted_long": 0.0028411050145513263,
        "adg_weighted_per_exposure_long": 0.0028411050145513263,
        "adg_weighted_per_exposure_short": 0.0,
        "adg_weighted_short": 0.0,
        "avg_fills_per_day_long": 15.248316017810254,
        "avg_fills_per_day_short": 0.0,
        "closest_bkr_long": 0.9750461981781041,
        "closest_bkr_short": 1.0,
        "drawdown_1pct_worst_mean_long": 0.2828318580855495,
        "drawdown_1pct_worst_mean_short": -0.0,
        "drawdown_max_long": 0.34155836564214437,
        "drawdown_max_short": -0.0,
        "eqbal_ratio_mean_long": 0.9918850232765694,
        "eqbal_ratio_mean_of_10_worst_long": 0.7622847465543361,
        "eqbal_ratio_mean_of_10_worst_short": 1.0,
        "eqbal_ratio_mean_short": 1.0,
        "eqbal_ratio_min_long": 0.7425502674750383,
        "eqbal_ratio_min_short": NaN,
        "eqbal_ratio_std_long": 0.027770401688024415,
        "eqbal_ratio_std_short": 0.0,
        "equity_balance_ratio_mean_long": 0.9918850232765694,
        "equity_balance_ratio_mean_short": 1.0,
        "equity_balance_ratio_std_long": 0.027770401688024415,
        "equity_balance_ratio_std_short": 0.0,
        "exchange": "binance",
        "exposure_ratios_mean_long": 0.1661640404715933,
        "exposure_ratios_mean_short": NaN,
        "fee_sum_long": -65.4220956,
        "fee_sum_short": 0,
        "final_balance_long": 494.86675753792247,
        "final_balance_short": 300.0,
        "final_equity_long": 494.39970440000104,
        "final_equity_short": 300.0,
        "gain_long": 0.6495558584597416,
        "gain_short": 0.0,
        "hrs_stuck_avg_long": 1.5723011023244668,
        "hrs_stuck_avg_short": NaN,
        "hrs_stuck_max_long": 127.78333333333333,
        "hrs_stuck_max_short": NaN,
        "loss_profit_ratio_long": 0.22459044751835036,
        "loss_profit_ratio_short": 1.0,
        "loss_sum_long": -75.39034027010828,
        "loss_sum_short": 0,
        "n_closes_long": 3368,
        "n_closes_short": 0,
        "n_days": 364.9583333333333,
        "n_entries_long": 2197,
        "n_entries_short": 0,
        "n_fills_long": 5565,
        "n_fills_short": 0,
        "n_ientries_long": 1585,
        "n_ientries_short": 0,
        "n_normal_closes_long": 3145,
        "n_normal_closes_short": 0,
        "n_rentries_long": 612,
        "n_rentries_short": 0,
        "n_unstuck_closes_long": 223,
        "n_unstuck_closes_short": 0,
        "n_unstuck_entries_long": 0,
        "n_unstuck_entries_short": 0,
        "net_pnl_plus_fees_long": 194.86675753792147,
        "net_pnl_plus_fees_short": 0,
        "pa_distance_1pct_worst_mean_long": 0.2303077067856211,
        "pa_distance_1pct_worst_mean_short": 100.0,
        "pa_distance_max_long": 0.3463997956920977,
        "pa_distance_max_short": 100.0,
        "pa_distance_mean_long": 0.01865217388685045,
        "pa_distance_mean_short": 100.0,
        "pa_distance_std_long": 0.030893959866844345,
        "pa_distance_std_short": 1.0,
        "pnl_sum_long": 260.2888531379215,
        "pnl_sum_short": 0,
        "profit_sum_long": 335.67919340802973,
        "profit_sum_short": 0,
        "sharpe_ratio_long": 0.10795533156174564,
        "sharpe_ratio_short": 0.0,
        "starting_balance": 300.0,
        "symbol": "SOLUSDT",
        "time_at_max_exposure_long": 0.10547945205479452,
        "time_at_max_exposure_short": 0.0,
        "volume_quote_long": 219718.25678880245,
        "volume_quote_short": 0
    }
}