{"config_name": "recursive_grid_ICPUSDT_156days",
 "logging_level": 0,
 "long": {"auto_unstuck_delay_minutes": 1268.1976961761954,
          "auto_unstuck_ema_dist": 0.041677532489297786,
          "auto_unstuck_qty_pct": 0.01,
          "auto_unstuck_wallet_exposure_threshold": 0.1,
          "backwards_tp": false,
          "ddown_factor": 0.5578741182950754,
          "ema_span_0": 1099.88690149864,
          "ema_span_1": 582.3805705180756,
          "enabled": true,
          "initial_eprice_ema_dist": -0.007835021215149708,
          "initial_qty_pct": 0.03338068779974861,
          "markup_range": 0.0103227940755715,
          "min_markup": 0.014908936613205971,
          "n_close_orders": 6,
          "rentry_pprice_dist": 0.011875737452605272,
          "rentry_pprice_dist_wallet_exposure_weighting": 7.772520034596481,
          "wallet_exposure_limit": 1},
 "short": {"auto_unstuck_delay_minutes": 1432.8445648518164,
           "auto_unstuck_ema_dist": -0.08247114838023462,
           "auto_unstuck_qty_pct": 0.054228698691296054,
           "auto_unstuck_wallet_exposure_threshold": 0.20262869161663677,
           "backwards_tp": false,
           "ddown_factor": 2.6122891709427787,
           "ema_span_0": 1238.1167292138082,
           "ema_span_1": 1272.465552543955,
           "enabled": false,
           "initial_eprice_ema_dist": -0.07252205636373224,
           "initial_qty_pct": 0.045747166703232624,
           "markup_range": 0.04915512315913102,
           "min_markup": 0.0064654511404941915,
           "n_close_orders": 15,
           "rentry_pprice_dist": 0.043437022083816536,
           "rentry_pprice_dist_wallet_exposure_weighting": 3.1018597188474573,
           "wallet_exposure_limit": 1.0}}