{
    "market_type": "futures",
    "user": "bybit_readonly",
    "symbols": [
        "IMXUSDT"
    ],
    "latency_simulation_ms": 1000,
    "starting_balance": 1000.0,
    "start_date": "2020-06-14",
    "end_date": "2024-06-13",
    "slim_analysis": true,
    "base_dir": "/home/user/passivbot/backtests/pbgui",
    "ohlcv": true,
    "adg_n_subdivisions": 10,
    "enable_interactive_plot": false,
    "plot_theme": "light",
    "plot_candles_interval": "1m",
    "spot": false,
    "exchange": "bybit",
    "session_name": "2020-06-14_2024-06-13",
    "symbol": "IMXUSDT",
    "caches_dirpath": "/home/user/passivbot/backtests/pbgui/bybit/IMXUSDT/caches/",
    "plots_dirpath": "/home/user/passivbot/backtests/pbgui/bybit/IMXUSDT/plots/2024-06-24T121433/",
    "c_mult": 1.0,
    "hedge_mode": true,
    "inverse": false,
    "maker_fee": 0.0002,
    "min_cost": 0.0,
    "min_qty": 0.1,
    "price_step": 0.0001,
    "qty_step": 0.1,
    "taker_fee": 0.00055,
    "n_parts": null,
    "config_name": "recursive_grid_1_symbols_1460days",
    "logging_level": 0,
    "long": {
        "auto_unstuck_delay_minutes": 0.0,
        "auto_unstuck_ema_dist": 0.0,
        "auto_unstuck_qty_pct": 0.0,
        "auto_unstuck_wallet_exposure_threshold": 0.0,
        "backwards_tp": false,
        "ddown_factor": 0.41749233092462756,
        "ema_span_0": 251.9581845786689,
        "ema_span_1": 1120.065879304824,
        "enabled": true,
        "initial_eprice_ema_dist": 0.06999778326445213,
        "initial_qty_pct": 0.04,
        "markup_range": 0.011009794165939016,
        "min_markup": 0.01043606289788961,
        "n_close_orders": 2,
        "rentry_pprice_dist": 0.01886494103579766,
        "rentry_pprice_dist_wallet_exposure_weighting": 9.311101229038039,
        "wallet_exposure_limit": 1.0
    },
    "short": {
        "auto_unstuck_delay_minutes": 397.13606366070934,
        "auto_unstuck_ema_dist": -0.0881580122818652,
        "auto_unstuck_qty_pct": 0.043966482156326266,
        "auto_unstuck_wallet_exposure_threshold": 0.5184566999356576,
        "backwards_tp": false,
        "ddown_factor": 0.551109035829075,
        "ema_span_0": 42.415252409001795,
        "ema_span_1": 758.947107744643,
        "enabled": false,
        "initial_eprice_ema_dist": -0.06396193729132785,
        "initial_qty_pct": 0.018432957256647616,
        "markup_range": 0.01448949270529791,
        "min_markup": 0.004597668990580047,
        "n_close_orders": 5,
        "rentry_pprice_dist": 0.013519030097470745,
        "rentry_pprice_dist_wallet_exposure_weighting": 4.1993648919531985,
        "wallet_exposure_limit": 1.0
    },
    "disable_plotting": true,
    "passivbot_mode": "recursive_grid",
    "n_days": 931.7,
    "result": {
        "adg_long": 0.00027747591048132847,
        "adg_per_exposure_long": 0.00027747591048132847,
        "adg_per_exposure_short": 0.0,
        "adg_short": 0.0,
        "adg_weighted_long": 0.00021900337995564012,
        "adg_weighted_per_exposure_long": 0.00021900337995564012,
        "adg_weighted_per_exposure_short": 0.0,
        "adg_weighted_short": 0.0,
        "avg_fills_per_day_long": 1.1656529516994634,
        "avg_fills_per_day_short": 0.0,
        "closest_bkr_long": 1.0,
        "closest_bkr_short": 1.0,
        "drawdown_1pct_worst_mean_long": 0.00037589268088444785,
        "drawdown_1pct_worst_mean_short": -0.0,
        "drawdown_max_long": 0.008134539425559327,
        "drawdown_max_short": -0.0,
        "eqbal_ratio_mean_long": 0.999996973572421,
        "eqbal_ratio_mean_of_10_worst_long": 0.9953573771643155,
        "eqbal_ratio_mean_of_10_worst_short": 1.0,
        "eqbal_ratio_mean_short": 1.0,
        "eqbal_ratio_min_long": 0.9265546970602776,
        "eqbal_ratio_min_short": NaN,
        "eqbal_ratio_std_long": 0.0001315496975895296,
        "eqbal_ratio_std_short": 0.0,
        "equity_balance_ratio_mean_long": 0.999996973572421,
        "equity_balance_ratio_mean_short": 1.0,
        "equity_balance_ratio_std_long": 0.0001315496975895296,
        "equity_balance_ratio_std_short": 0.0,
        "exchange": "bybit",
        "exposure_ratios_mean_long": 0.00028672184381312265,
        "exposure_ratios_mean_short": 0.0,
        "fee_sum_long": -8.33447897,
        "fee_sum_short": 0,
        "final_balance_long": 1294.9592110299952,
        "final_balance_short": 1000.0,
        "final_equity_long": 1294.9592110299952,
        "final_equity_short": 1000.0,
        "gain_long": 0.2949592110299952,
        "gain_short": 0.0,
        "hrs_stuck_avg_long": 20.44832565284178,
        "hrs_stuck_avg_short": NaN,
        "hrs_stuck_max_long": 2009.6833333333334,
        "hrs_stuck_max_short": NaN,
        "loss_profit_ratio_long": 0.0,
        "loss_profit_ratio_short": 1.0,
        "loss_sum_long": 0.0,
        "loss_sum_short": 0,
        "n_closes_long": 645,
        "n_closes_short": 0,
        "n_days": 931.6666666666666,
        "n_entries_long": 441,
        "n_entries_short": 0,
        "n_fills_long": 1086,
        "n_fills_short": 0,
        "n_ientries_long": 249,
        "n_ientries_short": 0,
        "n_normal_closes_long": 645,
        "n_normal_closes_short": 0,
        "n_rentries_long": 192,
        "n_rentries_short": 0,
        "n_unstuck_closes_long": 0,
        "n_unstuck_closes_short": 0,
        "n_unstuck_entries_long": 0,
        "n_unstuck_entries_short": 0,
        "net_pnl_plus_fees_long": 294.9592110299996,
        "net_pnl_plus_fees_short": 0,
        "pa_distance_1pct_worst_mean_long": 0.010372966774643376,
        "pa_distance_1pct_worst_mean_short": 100.0,
        "pa_distance_max_long": 0.04468760520431852,
        "pa_distance_max_short": 100.0,
        "pa_distance_mean_long": 0.01037296677464338,
        "pa_distance_mean_short": 100.0,
        "pa_distance_std_long": 0.008172912140551209,
        "pa_distance_std_short": 1.0,
        "pnl_sum_long": 303.29368999999963,
        "pnl_sum_short": 0,
        "profit_sum_long": 303.29368999999963,
        "profit_sum_short": 0,
        "sharpe_ratio_long": 0.12820703417709728,
        "sharpe_ratio_short": 0.0,
        "starting_balance": 1000.0,
        "symbol": "IMXUSDT",
        "time_at_max_exposure_long": 0.0,
        "time_at_max_exposure_short": 0.0,
        "volume_quote_long": 59280.04642398222,
        "volume_quote_short": 0
    }
}